lkcef_python.cpython-311-darwin.so
livekit/plugins/browser/__init__.py
livekit/plugins/browser/log.py
livekit/plugins/browser/proc.py
livekit/plugins/browser/proc_main.py
livekit/plugins/browser/proto.py
livekit/plugins/browser/py.typed
livekit/plugins/browser/version.py
livekit/plugins/browser/resources/__init__.py
livekit/plugins/browser/resources/lkcef_app.app/Contents/Info.plist
livekit/plugins/browser/resources/lkcef_app.app/Contents/Frameworks/Chromium Embedded Framework.framework/Chromium Embedded Framework
livekit/plugins/browser/resources/lkcef_app.app/Contents/Frameworks/Chromium Embedded Framework.framework/Libraries/libEGL.dylib
livekit/plugins/browser/resources/lkcef_app.app/Contents/Frameworks/Chromium Embedded Framework.framework/Libraries/libGLESv2.dylib
livekit/plugins/browser/resources/lkcef_app.app/Contents/Frameworks/Chromium Embedded Framework.framework/Libraries/libvk_swiftshader.dylib
livekit/plugins/browser/resources/lkcef_app.app/Contents/Frameworks/Chromium Embedded Framework.framework/Libraries/vk_swiftshader_icd.json
livekit/plugins/browser/resources/lkcef_app.app/Contents/Frameworks/Chromium Embedded Framework.framework/Resources/Info.plist
livekit/plugins/browser/resources/lkcef_app.app/Contents/Frameworks/Chromium Embedded Framework.framework/Resources/chrome_100_percent.pak
livekit/plugins/browser/resources/lkcef_app.app/Contents/Frameworks/Chromium Embedded Framework.framework/Resources/chrome_200_percent.pak
livekit/plugins/browser/resources/lkcef_app.app/Contents/Frameworks/Chromium Embedded Framework.framework/Resources/gpu_shader_cache.bin
livekit/plugins/browser/resources/lkcef_app.app/Contents/Frameworks/Chromium Embedded Framework.framework/Resources/icudtl.dat
livekit/plugins/browser/resources/lkcef_app.app/Contents/Frameworks/Chromium Embedded Framework.framework/Resources/resources.pak
livekit/plugins/browser/resources/lkcef_app.app/Contents/Frameworks/Chromium Embedded Framework.framework/Resources/snapshot_blob.bin
livekit_plugins_browser-0.0.7.dist-info/licenses/LICENSE.txt
livekit_plugins_browser-0.0.7.dist-info/METADATA
livekit_plugins_browser-0.0.7.dist-info/WHEEL
livekit_plugins_browser-0.0.7.dist-info/top_level.txt
livekit_plugins_browser-0.0.7.dist-info/RECORD
